{"version":1415160351,"duration":2006011,"pause":0,"calories":508,"subjective_feeling":"good","plausible":true,"start_time_timezone_offset":7200000,"end_time_timezone_offset":7200000,"tracking_method":"tracked","start_time":1343065943000,"end_time":1343067949000,"user_perceived_start_time":1343073143000,"user_perceived_end_time":1343075149000,"created_at":1343065936000,"updated_at":1643292330000,"features":[{"type":"weather","attributes":{"conditions":"sunny","temperature":25.0}},{"type":"map","attributes":{"encoded_trace":"c_fhH}tkLJu@?iK}@wMyA}FiBgH{AiImAyFsAcG[mIWoDaAoGaBkHYeHTwJKuDu@uJmBoFiBuH}Ac@cBu@iCsEiAcHw@_HMoGKaDIwH?uHEgGW_FUmCgCgHoCmHcBqEgAyBcBqC{CcFwCsEcAkBoCcEyCsDyD{D_Bm@kAyBmD_CsEsHgAaBkDg@iFc@{CgB","trace_available":true,"start_latitude":48.696342,"start_longitude":2.194873}},{"type":"track_metrics","attributes":{"distance":5134,"average_speed":"2.5593079998065815","average_pace":0.3907306194000779,"max_speed":"7.0777777777777775","elevation_gain":89,"elevation_loss":74,"surface":"mixed"}},{"type":"heart_rate","attributes":{"average":0,"maximum":0,"trace_available":false}},{"type":"initial_values","attributes":{"distance":5134,"duration":2006011,"pause":0,"sport_type":{"id":"1","type":"sport_type"},"start_time":1343065943000,"end_time":1343067949000}},{"type":"origin","attributes":{"device":{"name":"HTC Desire","vendor":"HTC","os_version":"Android 2.3.3"}}}],"id":"55e3c83577893f9f87c3d22a","user_id":"9e980000-7cb0-a9d1-a93a-633e603929c8","sport_type_id":"1","creation_application_id":"457"}