{"version":2,"duration":2700000,"pause":0,"calories":742,"subjective_feeling":"awesome","dehydration_volume":1027,"plausible":true,"start_time_timezone_offset":7200000,"end_time_timezone_offset":7200000,"tracking_method":"manual","start_time":1686846080000,"end_time":1686848780000,"user_perceived_start_time":1686853280000,"user_perceived_end_time":1686855980000,"created_at":1687108918000,"updated_at":1687108918000,"features":[{"type":"weather","attributes":{"conditions":"night"}},{"type":"track_metrics","attributes":{"distance":7000,"average_speed":"2.5925925925925926","average_pace":"0.38571428571428573","max_speed":0.0,"elevation_gain":0,"elevation_loss":0,"surface":"beach"}},{"type":"fastest_segments","attributes":{"segments":[{"distance":"1km","duration":385714,"started_at":1686846080000},{"distance":"1mi","duration":621000,"started_at":1686846080000},{"distance":"3mi","duration":1863000,"started_at":1686846080000},{"distance":"5km","duration":1928571,"started_at":1686846080000}]}},{"type":"heart_rate","attributes":{"average":0,"maximum":0,"trace_available":false}},{"type":"initial_values","attributes":{"distance":7000,"duration":2700000,"pause":0,"sport_type":{"id":"1","type":"sport_type"},"start_time":1686846080000,"end_time":1686848780000}},{"type":"origin","attributes":{"device":{"name":"Pixel 6a","vendor":"Google","os_version":"Android 13"}}}],"id":"76387637-fd7c-4c93-a2a7-466acf81f8cd","user_id":"9e980000-7cb0-a9d1-a93a-633e603929c8","sport_type_id":"1","creation_application_id":"3177"}